[
  {
    "full_name": "Guest One",
    "phone": "1112223333",
    "company": "Test Corp",
    "email": "1112223333@example.com",
    "notes": null,
    "table_id": null,
    "seat_id": null,
    "checked_in": false,
    "checked_in_at": null,
    "checked_in_by": null,
    "id": "aa82f2ed-104e-46fb-b0ed-71a17d70e447",
    "event_id": "EV2BD9B68D",
    "created_at": "2026-01-31T08:11:31.416168",
    "updated_at": "2026-01-31T08:11:31.416168"
  },
  {
    "full_name": "Guest Three",
    "phone": "4445556666",
    "company": "Test Corp",
    "email": "4445556666@example.com",
    "notes": null,
    "table_id": null,
    "seat_id": null,
    "checked_in": false,
    "checked_in_at": null,
    "checked_in_by": null,
    "id": "aa4a1f41-05cb-4874-85f2-92b3ea2aeeb2",
    "event_id": "EV2BD9B68D",
    "created_at": "2026-01-31T08:11:35.547918",
    "updated_at": "2026-01-31T08:11:35.547918"
  },
  {
    "full_name": "Guest Four",
    "phone": "7778889999",
    "company": "Test Corp",
    "email": "7778889999@example.com",
    "notes": null,
    "table_id": null,
    "seat_id": null,
    "checked_in": false,
    "checked_in_at": null,
    "checked_in_by": null,
    "id": "f804cc31-36e1-40e0-9d2d-21e881392c57",
    "event_id": "EV2BD9B68D",
    "created_at": "2026-01-31T08:11:37.611450",
    "updated_at": "2026-01-31T08:11:37.611450"
  }
]